cloudkitect/components/__init__.py
cloudkitect/components/py.typed
cloudkitect/components/_jsii/__init__.py
cloudkitect/components/_jsii/components@1.4.1.jsii.tgz
cloudkitect.components-1.4.1.dist-info/LICENSE
cloudkitect.components-1.4.1.dist-info/METADATA
cloudkitect.components-1.4.1.dist-info/WHEEL
cloudkitect.components-1.4.1.dist-info/top_level.txt
cloudkitect.components-1.4.1.dist-info/RECORD
